[
  {
    "heading": "Architecture",
    "data": [
      {
        "text": "Architecture History",
        "link": "/"
      },
      {
        "text": "Architectural Restoration",
        "link": "/"
      },
      {
        "text": "Dynamics",
        "link": "/"
      },
      {
        "text": "History",
        "link": "/"
      },
      {
        "text": "Housing",
        "link": "/"
      },
      {
        "text": "Physics",
        "link": "/"
      },
      {
        "text": "Railway Engineering",
        "link": "/"
      },
      {
        "text": "Religion",
        "link": "/"
      },
      {
        "text": "Steel",
        "link": "/"
      },
      {
        "text": "Vernacular Architecture",
        "link": "/"
      },
      {
        "text": "World History",
        "link": "/"
      }
    ]
  },
  {
    "heading": "Arts",
    "data": [
      {
        "text": "Animation",
        "link": "/"
      },
      {
        "text": "Architecture",
        "link": "/"
      },
      {
        "text": "Architectural Restoration",
        "link": "/"
      },
      {
        "text": "Art History",
        "link": "/"
      },
      {
        "text": "Blender Tutorial",
        "link": "/"
      },
      {
        "text": "Cartography",
        "link": "/"
      },
      {
        "text": "CGI Animation",
        "link": "/"
      },
      {
        "text": "Counseling",
        "link": "/"
      },
      {
        "text": "Creativity",
        "link": "/"
      },
      {
        "text": "Culture",
        "link": "/"
      },
      {
        "text": "Design",
        "link": "/"
      },
      {
        "text": "Drawing",
        "link": "/"
      },
      {
        "text": "Film",
        "link": "/"
      },
      {
        "text": "Fun",
        "link": "/"
      },
      {
        "text": "Humanities",
        "link": "/"
      },
      {
        "text": "Memes",
        "link": "/"
      },
      {
        "text": "Music",
        "link": "/"
      },
      {
        "text": "Music and Arts",
        "link": "/"
      },
      {
        "text": "Music Theory",
        "link": "/"
      },
      {
        "text": "Mythology",
        "link": "/"
      },
      {
        "text": "Popular Culture",
        "link": "/"
      },
      {
        "text": "Procedural Modeling",
        "link": "/"
      }
    ]
  },
  {
    "heading": "Computer Programming",
    "data": [
      {
        "text": ".NET",
        "link": "/"
      },
      {
        "text": "Algorithms",
        "link": "/"
      },
      {
        "text": "AWS",
        "link": "/"
      },
      {
        "text": "Android Development",
        "link": "/"
      },
      {
        "text": "Angular",
        "link": "/"
      },
      {
        "text": "Apache Spark",
        "link": "/"
      },
      {
        "text": "App Development",
        "link": "/"
      },
      {
        "text": "Azure",
        "link": "/"
      },
      {
        "text": "Blockchain",
        "link": "/"
      },
      {
        "text": "Bootstrap",
        "link": "/"
      },
      {
        "text": "C Programming",
        "link": "/"
      },
      {
        "text": "C#",
        "link": "/"
      },
      {
        "text": "Chatbots",
        "link": "/"
      },
      {
        "text": "Cloud Computing",
        "link": "/"
      },
      {
        "text": "Cloud Foundry",
        "link": "/"
      },
      {
        "text": "Coding",
        "link": "/"
      }
    ]
  }
]
